{
	"credit": "Made by WillowKoishi",
	"render_type": "translucent",
	"texture_size": [32, 32],
	"textures": {
		"0": "kuayue:block/hxd3d/door/hxd3d_door_bottom",
		"particle": "kuayue:block/hxd3d/door/hxd3d_door_bottom"
	},
	"elements": [
		{
			"from": [11, 0, 15.5],
			"to": [16, 16, 16.5],
			"rotation": {"angle": 0, "axis": "y", "origin": [14, 0, 15]},
			"faces": {
				"north": {"uv": [0, 0, 2.5, 8], "texture": "#0"},
				"east": {"uv": [8, 2, 8.5, 10], "texture": "#0"},
				"south": {"uv": [2.5, 0, 5, 8], "texture": "#0"},
				"west": {"uv": [4, 8, 4.5, 16], "texture": "#0"},
				"up": {"uv": [8, 8.5, 5.5, 8], "texture": "#0"},
				"down": {"uv": [11, 3, 8.5, 3.5], "texture": "#0"}
			}
		},
		{
			"from": [0, 0, 15.5],
			"to": [4, 16, 16.5],
			"rotation": {"angle": 0, "axis": "y", "origin": [3, 0, 15]},
			"faces": {
				"north": {"uv": [5, 0, 7, 8], "texture": "#0"},
				"east": {"uv": [4.5, 8, 5, 16], "texture": "#0"},
				"south": {"uv": [9.75, 8, 11.75, 16], "texture": "#0"},
				"west": {"uv": [5, 8, 5.5, 16], "texture": "#0"},
				"up": {"uv": [10, 6, 8.5, 5.5], "texture": "#0"},
				"down": {"uv": [7.5, 8.5, 6, 9], "texture": "#0"}
			}
		},
		{
			"from": [4, 0, 15.5],
			"to": [11, 4, 16.5],
			"rotation": {"angle": 0, "axis": "y", "origin": [3, 0, 15]},
			"faces": {
				"north": {"uv": [0, 8, 4, 10], "texture": "#0"},
				"east": {"uv": [8.5, 3.5, 9, 5.5], "texture": "#0"},
				"south": {"uv": [8, 0, 12, 2], "texture": "#0"},
				"west": {"uv": [5.5, 8.5, 6, 10.5], "texture": "#0"},
				"up": {"uv": [12.5, 2.5, 8.5, 2], "texture": "#0"},
				"down": {"uv": [12.5, 2.5, 8.5, 3], "texture": "#0"}
			}
		},
		{
			"from": [12, 4, 15.5],
			"to": [13, 16, 22.5],
			"rotation": {"angle": 22.5, "axis": "y", "origin": [12.5, 10, 19]},
			"faces": {
				"north": {"uv": [0.25, 0.25, 0.75, 6.25], "texture": "#0"},
				"east": {"uv": [3.25, 2.75, 4.25, 5.5], "texture": "#0"},
				"south": {"uv": [1.25, 0.75, 1.75, 6.75], "texture": "#0"},
				"west": {"uv": [12, 3, 16, 9], "texture": "#0"},
				"up": {"uv": [1, 9, 5, 9.5], "rotation": 270, "texture": "#0"},
				"down": {"uv": [1, 8.25, 5, 8.75], "rotation": 90, "texture": "#0"}
			}
		}
	]
}